build
dist
docs
examples
ompl_core
opof_sbmp
smbp_core
tests
